Metadata-Version: 1.0
Name: video-ferramentas
Version: 1.0
Summary: Este pacote irá fornecer ferramentas de processsamento de vídeo
Home-page: UNKNOWN
Author: Geovano
Author-email: exemplo@gmail.com
License: UNKNOWN
Keywords: camera,video,processamento
Platform: UNKNOWN
